ryuso/__init__.py
ryuso/__main__.py
ryuso/hook.py
ryuso/orchestrator.py
ryuso/orchestrator_server.py
ryuso/util.py
ryuso/templates/__init__.py.temp
ryuso/templates/__main__.py.temp
ryuso/templates/func_defs.py.temp
ryuso-0.0.8.dist-info/METADATA
ryuso-0.0.8.dist-info/WHEEL
ryuso-0.0.8.dist-info/entry_points.txt
ryuso-0.0.8.dist-info/top_level.txt
ryuso-0.0.8.dist-info/RECORD
