Metadata-Version: 2.1
Name: ryuso
Version: 0.0.8
Summary: A framework for creating a set of remotely executed programs built from a sequence of functions with optional reversibility
Home-page: https://gitlab.com/delta1512/ryu-sequential-orchestrator
Author: Marcus Belcastro
Author-email: markbel555@gmail.com
License: GNU GPLv3
Project-URL: Donate, https://gitlab.com/delta1512/donations
Project-URL: Source Code, https://gitlab.com/delta1512/ryu-sequential-orchestrator
Project-URL: Twitter, https://twitter.com/delta_1512
Platform: UNKNOWN
